fabriq/__init__.py
fabriq/config_parser.py
fabriq/agents/__init__.py
fabriq/agents/agents.py
fabriq/chatbot/__init__.py
fabriq/chatbot/chat_cli.py
fabriq/chatbot/chat_ui.py
fabriq/chatbot/ui_runner.py
fabriq/document_loader/__init__.py
fabriq/document_loader/doc_utils.py
fabriq/document_loader/document_loader.py
fabriq/embeddings/__init__.py
fabriq/embeddings/embeddings.py
fabriq/evaluation/__init__.py
fabriq/evaluation/evaluation.py
fabriq/fabriq_tools/__init__.py
fabriq/fabriq_tools/clinical_trials.py
fabriq/fabriq_tools/code_analysis.py
fabriq/fabriq_tools/datetime_tool.py
fabriq/fabriq_tools/file_reader.py
fabriq/fabriq_tools/translator.py
fabriq/fabriq_tools/travel_tool.py
fabriq/fabriq_tools/web_search.py
fabriq/fabriq_tools/wiki.py
fabriq/fabriq_tools/wolfram.py
fabriq/fabriq_tools/yahoo_finance_news.py
fabriq/fabriq_tools/youtube.py
fabriq/guardrails/__init__.py
fabriq/guardrails/guardrails.py
fabriq/indexing/__init__.py
fabriq/indexing/indexing.py
fabriq/llm/__init__.py
fabriq/llm/llm.py
fabriq/metadata/__init__.py
fabriq/metadata/metadata_enrich.py
fabriq/rag_pipeline/__init__.py
fabriq/rag_pipeline/rag_pipeline.py
fabriq/reranking/__init__.py
fabriq/reranking/reranker.py
fabriq/retriever/__init__.py
fabriq/retriever/bm25_retriever.py
fabriq/retriever/hybrid_retriever.py
fabriq/retriever/vector_retriever.py
fabriq/text_splitter/__init__.py
fabriq/text_splitter/text_splitter.py
fabriq/vector_store/__init__.py
fabriq/vector_store/bm25_store.py
fabriq/vector_store/vector_store.py
fabriq/wardrobe/__init__.py
fabriq/wardrobe/bank_statement_parser.py
fabriq/wardrobe/ner.py
fabriq/wardrobe/resume_matcher.py
fabriq/wardrobe/resume_parser.py
fabriq/wardrobe/text_classification.py
fabriq/wardrobe/text_summarization.py
fabriq/wardrobe/video_analysis.py
fabriq-0.2.9.8.dist-info/METADATA
fabriq-0.2.9.8.dist-info/WHEEL
fabriq-0.2.9.8.dist-info/entry_points.txt
fabriq-0.2.9.8.dist-info/top_level.txt
fabriq-0.2.9.8.dist-info/RECORD
