Metadata-Version: 2.4
Name: fabriq
Version: 0.2.9.8
Summary: Fabriq is a Python SDK for developing quick, low code Generative AI solutions.
Home-page: https://github.com/Aaryanverma/fabriq
Author: Aaryan Verma
License: MIT
Classifier: Programming Language :: Python :: 3
Classifier: Programming Language :: Python :: 3.10
Classifier: Programming Language :: Python :: 3.11
Classifier: Programming Language :: Python :: 3.12
Classifier: License :: OSI Approved :: MIT License
Classifier: Operating System :: Microsoft :: Windows
Classifier: Operating System :: MacOS
Classifier: Operating System :: POSIX :: Linux
Requires-Python: >=3.10
Requires-Dist: azure-ai-inference==1.0.0b9
Requires-Dist: langchain==1.2.0
Requires-Dist: langchain_classic==1.0.1
Requires-Dist: langchain_community==0.4.1
Requires-Dist: langchain_core==1.2.5
Requires-Dist: numpy
Requires-Dist: pandas
Requires-Dist: Pillow==11.3.0
Requires-Dist: pydantic==2.11.7
Requires-Dist: python-dotenv==1.1.1
Requires-Dist: PyYAML==6.0.2
Requires-Dist: Requests==2.32.4
Requires-Dist: setuptools
Requires-Dist: langchain_experimental==0.4.1
Requires-Dist: tenacity==8.2.3
Requires-Dist: streamlit==1.52.2
Provides-Extra: chat
Requires-Dist: langchain-google_genai==4.1.2; extra == "chat"
Requires-Dist: langchain-groq==1.1.1; extra == "chat"
Requires-Dist: langchain-huggingface==1.2.0; extra == "chat"
Requires-Dist: langchain-mistralai==1.1.1; extra == "chat"
Requires-Dist: langchain-ollama==1.0.1; extra == "chat"
Requires-Dist: langchain-openai==1.1.6; extra == "chat"
Requires-Dist: langchain-aws==1.1.1; extra == "chat"
Requires-Dist: langchain-azure_ai==1.0.4; extra == "chat"
Requires-Dist: openai==2.14.0; extra == "chat"
Requires-Dist: torch; extra == "chat"
Requires-Dist: transformers==4.53.2; extra == "chat"
Requires-Dist: azure-ai-inference==1.0.0b9; extra == "chat"
Requires-Dist: fitz==0.0.1.dev2; extra == "chat"
Requires-Dist: langchain-text-splitters==1.1.0; extra == "chat"
Requires-Dist: markitdown==0.1.2; extra == "chat"
Requires-Dist: openpyxl==3.1.5; extra == "chat"
Requires-Dist: pymupdf4llm==0.0.27; extra == "chat"
Requires-Dist: python_docx==1.1.2; extra == "chat"
Requires-Dist: python_magic==0.4.27; extra == "chat"
Requires-Dist: python_pptx==1.0.2; extra == "chat"
Requires-Dist: tabulate==0.9.0; extra == "chat"
Requires-Dist: unstructured==0.17.2; extra == "chat"
Requires-Dist: docling==2.52.0; extra == "chat"
Requires-Dist: langchain-postgres==0.0.16; extra == "chat"
Requires-Dist: langchain-chroma==0.2.5; extra == "chat"
Requires-Dist: langgraph-checkpoint-postgres==3.0.2; extra == "chat"
Requires-Dist: scikit-learn; extra == "chat"
Requires-Dist: cohere==5.20.1; extra == "chat"
Requires-Dist: streamlit==1.41.1; extra == "chat"
Requires-Dist: sentence_transformers==3.3.1; extra == "chat"
Provides-Extra: agents
Requires-Dist: crewai==1.7.2; extra == "agents"
Requires-Dist: crewai[tools]==1.7.2; extra == "agents"
Provides-Extra: doc-loader
Requires-Dist: fitz==0.0.1.dev2; extra == "doc-loader"
Requires-Dist: langchain-text-splitters==1.1.0; extra == "doc-loader"
Requires-Dist: markitdown==0.1.2; extra == "doc-loader"
Requires-Dist: openpyxl==3.1.5; extra == "doc-loader"
Requires-Dist: pymupdf4llm==0.0.27; extra == "doc-loader"
Requires-Dist: python_docx==1.1.2; extra == "doc-loader"
Requires-Dist: python_magic==0.4.27; extra == "doc-loader"
Requires-Dist: python_pptx==1.0.2; extra == "doc-loader"
Requires-Dist: tabulate==0.9.0; extra == "doc-loader"
Requires-Dist: unstructured==0.17.2; extra == "doc-loader"
Requires-Dist: docling==2.52.0; extra == "doc-loader"
Requires-Dist: openai-whisper==20250625; extra == "doc-loader"
Provides-Extra: index
Requires-Dist: langchain-google_genai==4.1.2; extra == "index"
Requires-Dist: langchain-groq==1.1.1; extra == "index"
Requires-Dist: langchain-huggingface==1.2.0; extra == "index"
Requires-Dist: langchain-mistralai==1.1.1; extra == "index"
Requires-Dist: langchain-ollama==1.0.1; extra == "index"
Requires-Dist: langchain-openai==1.1.6; extra == "index"
Requires-Dist: langchain-aws==1.1.1; extra == "index"
Requires-Dist: langchain-azure_ai==1.0.4; extra == "index"
Requires-Dist: openai==2.14.0; extra == "index"
Requires-Dist: torch; extra == "index"
Requires-Dist: transformers==4.53.2; extra == "index"
Requires-Dist: azure-ai-inference==1.0.0b9; extra == "index"
Requires-Dist: docling==2.52.0; extra == "index"
Provides-Extra: rag
Requires-Dist: langchain-google_genai==4.1.2; extra == "rag"
Requires-Dist: langchain-groq==1.1.1; extra == "rag"
Requires-Dist: langchain-huggingface==1.2.0; extra == "rag"
Requires-Dist: langchain-mistralai==1.1.1; extra == "rag"
Requires-Dist: langchain-ollama==1.0.1; extra == "rag"
Requires-Dist: langchain-openai==1.1.6; extra == "rag"
Requires-Dist: langchain-aws==1.1.1; extra == "rag"
Requires-Dist: langchain-azure_ai==1.0.4; extra == "rag"
Requires-Dist: openai==2.14.0; extra == "rag"
Requires-Dist: torch; extra == "rag"
Requires-Dist: transformers==4.53.2; extra == "rag"
Requires-Dist: azure-ai-inference==1.0.0b9; extra == "rag"
Requires-Dist: fitz==0.0.1.dev2; extra == "rag"
Requires-Dist: langchain-text-splitters==0.3.9; extra == "rag"
Requires-Dist: markitdown==0.1.2; extra == "rag"
Requires-Dist: openpyxl==3.1.5; extra == "rag"
Requires-Dist: pymupdf4llm==0.0.27; extra == "rag"
Requires-Dist: python_docx==1.1.2; extra == "rag"
Requires-Dist: python_magic==0.4.27; extra == "rag"
Requires-Dist: python_pptx==1.0.2; extra == "rag"
Requires-Dist: tabulate==0.9.0; extra == "rag"
Requires-Dist: unstructured==0.17.2; extra == "rag"
Requires-Dist: langchain-postgres==0.0.16; extra == "rag"
Requires-Dist: langchain-chroma==1.1.0; extra == "rag"
Requires-Dist: langgraph-checkpoint-postgres==3.0.2; extra == "rag"
Requires-Dist: scikit-learn; extra == "rag"
Requires-Dist: cohere==5.20.1; extra == "rag"
Requires-Dist: docling==2.52.0; extra == "rag"
Requires-Dist: sentence_transformers==3.3.1; extra == "rag"
Provides-Extra: tools
Requires-Dist: amadeus==12.0.0; extra == "tools"
Requires-Dist: azure-ai-inference==1.0.0b9; extra == "tools"
Requires-Dist: azure_storage==0.37.0; extra == "tools"
Requires-Dist: ddgs==9.5.1; extra == "tools"
Requires-Dist: langchain-experimental==0.4.1; extra == "tools"
Requires-Dist: langchain-google_genai==4.1.2; extra == "tools"
Requires-Dist: langchain-groq==1.1.1; extra == "tools"
Requires-Dist: langchain-huggingface==1.2.0; extra == "tools"
Requires-Dist: langchain-mistralai==1.1.1; extra == "tools"
Requires-Dist: langchain-ollama==1.0.1; extra == "tools"
Requires-Dist: langchain-openai==1.1.6; extra == "tools"
Requires-Dist: langchain-aws==1.1.1; extra == "tools"
Requires-Dist: langchain-azure_ai==1.0.4; extra == "tools"
Requires-Dist: openai==2.14.0; extra == "tools"
Requires-Dist: pytrials==1.0.0; extra == "tools"
Requires-Dist: youtube_search==2.1.2; extra == "tools"
Requires-Dist: deep_translator==1.11.4; extra == "tools"
Provides-Extra: evals
Requires-Dist: azure-ai-inference==1.0.0b9; extra == "evals"
Requires-Dist: deepeval==3.3.4; extra == "evals"
Requires-Dist: langchain-google_genai==4.1.2; extra == "evals"
Requires-Dist: langchain-groq==1.1.1; extra == "evals"
Requires-Dist: langchain-huggingface==1.2.0; extra == "evals"
Requires-Dist: langchain-mistralai==1.1.1; extra == "evals"
Requires-Dist: langchain-ollama==1.0.1; extra == "evals"
Requires-Dist: langchain-openai==1.1.6; extra == "evals"
Requires-Dist: langchain-aws==1.1.1; extra == "evals"
Requires-Dist: langchain-azure_ai==1.0.4; extra == "evals"
Requires-Dist: openai==2.14.0; extra == "evals"
Requires-Dist: torch; extra == "evals"
Requires-Dist: transformers==4.53.2; extra == "evals"
Provides-Extra: trace
Requires-Dist: mlflow==3.8.1; extra == "trace"
Provides-Extra: all
Requires-Dist: azure-ai-inference==1.0.0b9; extra == "all"
Requires-Dist: langchain==1.2.0; extra == "all"
Requires-Dist: langchain_classic==1.0.1; extra == "all"
Requires-Dist: langchain_community==0.4.1; extra == "all"
Requires-Dist: langchain_core==1.2.5; extra == "all"
Requires-Dist: numpy; extra == "all"
Requires-Dist: pandas; extra == "all"
Requires-Dist: Pillow==11.3.0; extra == "all"
Requires-Dist: pydantic==2.11.7; extra == "all"
Requires-Dist: python-dotenv==1.1.1; extra == "all"
Requires-Dist: PyYAML==6.0.2; extra == "all"
Requires-Dist: Requests==2.32.4; extra == "all"
Requires-Dist: setuptools; extra == "all"
Requires-Dist: langchain_experimental==0.4.1; extra == "all"
Requires-Dist: tenacity==8.2.3; extra == "all"
Requires-Dist: streamlit==1.52.2; extra == "all"
Requires-Dist: fitz==0.0.1.dev2; extra == "all"
Requires-Dist: langchain-text-splitters==1.1.0; extra == "all"
Requires-Dist: markitdown==0.1.2; extra == "all"
Requires-Dist: openpyxl==3.1.5; extra == "all"
Requires-Dist: pymupdf4llm==0.0.27; extra == "all"
Requires-Dist: python_docx==1.1.2; extra == "all"
Requires-Dist: python_magic==0.4.27; extra == "all"
Requires-Dist: python_pptx==1.0.2; extra == "all"
Requires-Dist: tabulate==0.9.0; extra == "all"
Requires-Dist: unstructured==0.17.2; extra == "all"
Requires-Dist: docling==2.52.0; extra == "all"
Requires-Dist: openai-whisper==20250625; extra == "all"
Requires-Dist: langchain-google_genai==4.1.2; extra == "all"
Requires-Dist: langchain-groq==1.1.1; extra == "all"
Requires-Dist: langchain-huggingface==1.2.0; extra == "all"
Requires-Dist: langchain-mistralai==1.1.1; extra == "all"
Requires-Dist: langchain-ollama==1.0.1; extra == "all"
Requires-Dist: langchain-openai==1.1.6; extra == "all"
Requires-Dist: langchain-aws==1.1.1; extra == "all"
Requires-Dist: langchain-azure_ai==1.0.4; extra == "all"
Requires-Dist: openai==2.14.0; extra == "all"
Requires-Dist: torch; extra == "all"
Requires-Dist: transformers==4.53.2; extra == "all"
Requires-Dist: azure-ai-inference==1.0.0b9; extra == "all"
Requires-Dist: docling==2.52.0; extra == "all"
Requires-Dist: langchain-google_genai==4.1.2; extra == "all"
Requires-Dist: langchain-groq==1.1.1; extra == "all"
Requires-Dist: langchain-huggingface==1.2.0; extra == "all"
Requires-Dist: langchain-mistralai==1.1.1; extra == "all"
Requires-Dist: langchain-ollama==1.0.1; extra == "all"
Requires-Dist: langchain-openai==1.1.6; extra == "all"
Requires-Dist: langchain-aws==1.1.1; extra == "all"
Requires-Dist: langchain-azure_ai==1.0.4; extra == "all"
Requires-Dist: openai==2.14.0; extra == "all"
Requires-Dist: torch; extra == "all"
Requires-Dist: transformers==4.53.2; extra == "all"
Requires-Dist: azure-ai-inference==1.0.0b9; extra == "all"
Requires-Dist: fitz==0.0.1.dev2; extra == "all"
Requires-Dist: langchain-text-splitters==0.3.9; extra == "all"
Requires-Dist: markitdown==0.1.2; extra == "all"
Requires-Dist: openpyxl==3.1.5; extra == "all"
Requires-Dist: pymupdf4llm==0.0.27; extra == "all"
Requires-Dist: python_docx==1.1.2; extra == "all"
Requires-Dist: python_magic==0.4.27; extra == "all"
Requires-Dist: python_pptx==1.0.2; extra == "all"
Requires-Dist: tabulate==0.9.0; extra == "all"
Requires-Dist: unstructured==0.17.2; extra == "all"
Requires-Dist: langchain-postgres==0.0.16; extra == "all"
Requires-Dist: langchain-chroma==1.1.0; extra == "all"
Requires-Dist: langgraph-checkpoint-postgres==3.0.2; extra == "all"
Requires-Dist: scikit-learn; extra == "all"
Requires-Dist: cohere==5.20.1; extra == "all"
Requires-Dist: docling==2.52.0; extra == "all"
Requires-Dist: sentence_transformers==3.3.1; extra == "all"
Requires-Dist: amadeus==12.0.0; extra == "all"
Requires-Dist: azure-ai-inference==1.0.0b9; extra == "all"
Requires-Dist: azure_storage==0.37.0; extra == "all"
Requires-Dist: ddgs==9.5.1; extra == "all"
Requires-Dist: langchain-experimental==0.4.1; extra == "all"
Requires-Dist: langchain-google_genai==4.1.2; extra == "all"
Requires-Dist: langchain-groq==1.1.1; extra == "all"
Requires-Dist: langchain-huggingface==1.2.0; extra == "all"
Requires-Dist: langchain-mistralai==1.1.1; extra == "all"
Requires-Dist: langchain-ollama==1.0.1; extra == "all"
Requires-Dist: langchain-openai==1.1.6; extra == "all"
Requires-Dist: langchain-aws==1.1.1; extra == "all"
Requires-Dist: langchain-azure_ai==1.0.4; extra == "all"
Requires-Dist: openai==2.14.0; extra == "all"
Requires-Dist: pytrials==1.0.0; extra == "all"
Requires-Dist: youtube_search==2.1.2; extra == "all"
Requires-Dist: deep_translator==1.11.4; extra == "all"
Requires-Dist: azure-ai-inference==1.0.0b9; extra == "all"
Requires-Dist: deepeval==3.3.4; extra == "all"
Requires-Dist: langchain-google_genai==4.1.2; extra == "all"
Requires-Dist: langchain-groq==1.1.1; extra == "all"
Requires-Dist: langchain-huggingface==1.2.0; extra == "all"
Requires-Dist: langchain-mistralai==1.1.1; extra == "all"
Requires-Dist: langchain-ollama==1.0.1; extra == "all"
Requires-Dist: langchain-openai==1.1.6; extra == "all"
Requires-Dist: langchain-aws==1.1.1; extra == "all"
Requires-Dist: langchain-azure_ai==1.0.4; extra == "all"
Requires-Dist: openai==2.14.0; extra == "all"
Requires-Dist: torch; extra == "all"
Requires-Dist: transformers==4.53.2; extra == "all"
Requires-Dist: langchain-google_genai==4.1.2; extra == "all"
Requires-Dist: langchain-groq==1.1.1; extra == "all"
Requires-Dist: langchain-huggingface==1.2.0; extra == "all"
Requires-Dist: langchain-mistralai==1.1.1; extra == "all"
Requires-Dist: langchain-ollama==1.0.1; extra == "all"
Requires-Dist: langchain-openai==1.1.6; extra == "all"
Requires-Dist: langchain-aws==1.1.1; extra == "all"
Requires-Dist: langchain-azure_ai==1.0.4; extra == "all"
Requires-Dist: openai==2.14.0; extra == "all"
Requires-Dist: torch; extra == "all"
Requires-Dist: transformers==4.53.2; extra == "all"
Requires-Dist: azure-ai-inference==1.0.0b9; extra == "all"
Requires-Dist: fitz==0.0.1.dev2; extra == "all"
Requires-Dist: langchain-text-splitters==1.1.0; extra == "all"
Requires-Dist: markitdown==0.1.2; extra == "all"
Requires-Dist: openpyxl==3.1.5; extra == "all"
Requires-Dist: pymupdf4llm==0.0.27; extra == "all"
Requires-Dist: python_docx==1.1.2; extra == "all"
Requires-Dist: python_magic==0.4.27; extra == "all"
Requires-Dist: python_pptx==1.0.2; extra == "all"
Requires-Dist: tabulate==0.9.0; extra == "all"
Requires-Dist: unstructured==0.17.2; extra == "all"
Requires-Dist: docling==2.52.0; extra == "all"
Requires-Dist: langchain-postgres==0.0.16; extra == "all"
Requires-Dist: langchain-chroma==0.2.5; extra == "all"
Requires-Dist: langgraph-checkpoint-postgres==3.0.2; extra == "all"
Requires-Dist: scikit-learn; extra == "all"
Requires-Dist: cohere==5.20.1; extra == "all"
Requires-Dist: streamlit==1.41.1; extra == "all"
Requires-Dist: sentence_transformers==3.3.1; extra == "all"
Requires-Dist: crewai==1.7.2; extra == "all"
Requires-Dist: crewai[tools]==1.7.2; extra == "all"
Requires-Dist: mlflow==3.8.1; extra == "all"
Dynamic: author
Dynamic: classifier
Dynamic: description
Dynamic: description-content-type
Dynamic: home-page
Dynamic: license
Dynamic: provides-extra
Dynamic: requires-dist
Dynamic: requires-python
Dynamic: summary
